typing_utilities-0.1.1.dist-info/licenses/LICENSE
typingutils/__init__.py
typingutils/internal.py
typingutils/core/attributes.py
typingutils/core/functions.py
typingutils/core/instances.py
typingutils/core/types.py
typingutils/core/compat/annotations.py
typingutils/core/compat/typevar_tuple.py
typing_utilities-0.1.1.dist-info/METADATA
typing_utilities-0.1.1.dist-info/WHEEL
typing_utilities-0.1.1.dist-info/top_level.txt
typing_utilities-0.1.1.dist-info/RECORD
