Metadata-Version: 2.4
Name: typing-utilities
Version: 0.1.1
Summary: Runtime reflection and validation of types and generics.
Author-email: Anders Madsen <anders.madsen@alphavue.com>
License-Expression: MIT
Project-URL: repository, https://github.com/apmadsen/typing-utilities
Keywords: windows,linux,generics,typing
Classifier: Development Status :: 5 - Production/Stable
Classifier: Development Status :: 6 - Mature
Classifier: Operating System :: Microsoft :: Windows
Classifier: Operating System :: POSIX :: Linux
Classifier: Intended Audience :: Developers
Classifier: Natural Language :: English
Classifier: Programming Language :: Python :: 3 :: Only
Classifier: Programming Language :: Python :: 3
Classifier: Programming Language :: Python :: 3.10
Classifier: Programming Language :: Python :: 3.11
Classifier: Programming Language :: Python :: 3.12
Classifier: Programming Language :: Python :: 3.13
Classifier: Programming Language :: Python
Classifier: Topic :: Software Development :: Libraries :: Python Modules
Classifier: Topic :: Software Development :: Libraries
Classifier: Typing :: Typed
Requires-Python: >=3.10
License-File: LICENSE
Requires-Dist: typing_extensions<5,>=4.13.2; python_version < "3.13"
Provides-Extra: test
Requires-Dist: pytest>=8.3; extra == "test"
Requires-Dist: pytest-cov>=6.1; extra == "test"
Requires-Dist: tox; extra == "test"
Dynamic: license-file
